<?xml version="1.0" encoding="UTF-8"?>
<objects serializationModel="Studio.02.02.00">
	<object class="ParameterPreset" id="{a84e0255-1cef-4d5e-9f57-85f4c8ad3f51}">
		<property name="name">
			<value>City</value>
		</property>
		<relationship name="folder">
			<destination>{28ad3f17-8a87-4047-a064-c25c0ee9095c}</destination>
		</relationship>
		<relationship name="parameter">
			<destination>{f26f4083-c56e-4c37-bc8b-f829445eb6e1}</destination>
		</relationship>
	</object>
	<object class="GameParameter" id="{f26f4083-c56e-4c37-bc8b-f829445eb6e1}">
		<property name="isGlobal">
			<value>true</value>
		</property>
		<property name="initialValue">
			<value>0</value>
		</property>
		<property name="isExposedRecursively">
			<value>false</value>
		</property>
	</object>
</objects>
